{"sections":{"main":{"type":"page-custom-four","disabled":true,"settings":{}},"3955e9cf-092a-4d98-8aa2-85a1aefe59c8":{"type":"page-custom-DataDim-template","blocks":{"9a734f4a-e343-43d7-8636-1be399901029":{"type":"page_content","settings":{"pc_align":"center","pc_max_width":800}},"a2830dd0-2291-4244-b2a2-fd34c1c1c468":{"type":"image_text_overlay","disabled":true,"settings":{"full_width":true,"image":"shopify:\/\/shop_images\/Contact_Us_462a40b3-2c0b-4747-91a3-a59bb39ce621.jpg","image_height":300,"heading":"Contact Us","hidden_text":"","link":"","button_text":"","heading_text_size":36,"hidden_text_size":18,"heading_color":"#000000","text_color":"#000000","button_text_color":"#ffffff","button_color":"#000000","section_padding":"bottom"}},"7c07c59d-53b4-42a8-bc38-f951b273e1ad":{"type":"image_carousel_with_text","disabled":true,"settings":{"ic_full_width":false,"ic_no_bottom_margin":false,"ic_layout":"left","ic_image_width":"50%","ic_text_align":"left","ic_title":"","ic_text":"<p><strong>Dealers & Distributors <\/strong><\/p><p>DENALI is actively seeking domestic dealers and international distributors in the Motorcycle, Powersports, and Automotive industries. <\/p><p>&gt; <a href=\"\/pages\/store-locator\" title=\"Store Locator\"><strong>Find a Dealer<\/strong><\/a><br\/>&gt; <a href=\"https:\/\/denalielectronics.com\/pages\/become-a-dealer\" title=\"https:\/\/denalielectronics.com\/pages\/become-a-dealer\"><strong>Become a Dealer<\/strong><\/a><br\/><br\/><br\/><strong>OEM & Custom Development<\/strong><\/p><p>In addition to developing the DENALI product line, we also supply OE manufacturers with custom engineered solutions. <\/p><p><a href=\"https:\/\/denalielectronics.com\/pages\/oe-manufacturing-product-development-program#page-section-ec263f70-0761-406c-ab99-f3a128d112e9\" target=\"_blank\" title=\"https:\/\/denalielectronics.com\/pages\/oe-manufacturing-product-development-program#page-section-ec263f70-0761-406c-ab99-f3a128d112e9\"><strong>&gt; OEM Services & Project Portfolio<\/strong><\/a><\/p>","ic_button":"Lean More","ic_link":"","ic_image_1":"shopify:\/\/shop_images\/Greg_MUD.jpg","ic_image_1_link":"","ic_image_2_link":""}}},"block_order":["9a734f4a-e343-43d7-8636-1be399901029","a2830dd0-2291-4244-b2a2-fd34c1c1c468","7c07c59d-53b4-42a8-bc38-f951b273e1ad"],"settings":{}},"f3d6a053-ebfa-4f47-8b5c-0fee6dd10511":{"type":"contact-form","blocks":{"ba6df812-ca20-442e-9bd0-b497064594e6":{"type":"text_input","settings":{"label":"Subject"}},"47dfc231-1ef7-42ed-81dd-28d6a34bfed3":{"type":"text_input","settings":{"label":"Shipping Address for Quotes"}},"text_input_f86aJ8":{"type":"text_input","settings":{"label":"State"}},"text_input_V6xrqw":{"type":"text_input","settings":{"label":"Postal Code"}},"text_input_3kWUCi":{"type":"text_input","settings":{"label":"Country"}},"text_input_hn3kmE":{"type":"text_input","settings":{"label":"Vehicle Make, Model, & Year"}}},"block_order":["ba6df812-ca20-442e-9bd0-b497064594e6","47dfc231-1ef7-42ed-81dd-28d6a34bfed3","text_input_f86aJ8","text_input_V6xrqw","text_input_3kWUCi","text_input_hn3kmE"],"disabled":true,"settings":{"cf_heading":"Shoot us an email","width":60,"cf_show_company_name":true,"cf_show_website_url":true,"cf_show_phone":true,"section_padding":"both"}},"c5c4b6eb-183a-4948-ad90-980a13999a00":{"type":"page-custom-DataDim-template","blocks":{"927e6919-3154-409f-ae84-721acaa55b42":{"type":"image_text_overlay","settings":{"full_width":true,"image":"shopify:\/\/shop_images\/Custom_Bike_Header_7dbe822a-5f6d-496e-a00a-92467e803380.jpg","image_height":600,"heading":"North American Dealers","hidden_text":"DENALI products are sold in many retail stores throughout North America. Below is a list of featured North American dealers. To see a complete list of all dealers in the US and Canada visit our North American Distributors website TwistedDistibuting.com.","link":"","button_text":"","heading_text_size":36,"hidden_text_size":14,"heading_color":"#ffffff","text_color":"#bdbdbd","button_text_color":"#ffffff","button_color":"#000000","section_padding":"both"}},"5fcc2c18-e331-4714-900b-a49ac632592c":{"type":"image_carousel_with_text","settings":{"ic_full_width":false,"ic_no_bottom_margin":false,"ic_layout":"left","ic_image_width":"50%","ic_text_align":"left","ic_title":"Featured North American Retailers","ic_text":"<p><strong>Shop our products in store & connect with experienced DENALI installers. <\/strong><\/p><p>Below is a list of featured North American DENALI dealers that have interactive DENALI displays and offer onsite product installations.<\/p><p><\/p>","ic_button":"View POS Displays","ic_link":"","ic_image_1":"shopify:\/\/shop_images\/Displays_800x800_6a21c02c-c77c-4ea9-8cf1-78b0baa14ee2.jpg","ic_image_1_link":"","ic_image_2_link":""}}},"block_order":["927e6919-3154-409f-ae84-721acaa55b42","5fcc2c18-e331-4714-900b-a49ac632592c"],"disabled":true,"settings":{}},"995b3ef3-a555-43d2-b97b-76cdd877f3e9":{"type":"editorial-columns","blocks":{"template--16427970003128__995b3ef3-a555-43d2-b97b-76cdd877f3e9-text_block-1":{"type":"text_block","settings":{"link":"","title_text":"Arizona","text":"<p><strong>Go Az Motorcycles<\/strong><br\/>15500 N Hayden RD<br\/>Scottsdale, Arizona 85260<br\/>(480)-609-1800<br\/><a href=\"https:\/\/www.goaz.com\/\" title=\"https:\/\/www.goaz.com\/\">https:\/\/www.goaz.com\/<\/a><\/p>","button_text":""}},"template--16427970003128__995b3ef3-a555-43d2-b97b-76cdd877f3e9-text_block-2":{"type":"text_block","settings":{"link":"","title_text":"Arizona","text":"<p><strong>Motoghost<\/strong><br\/>1628 N. Central Ave., Suite 1<br\/>Phoenix, AZ 85024 <br\/>(602)-324-9629<br\/><a href=\"http:\/\/motoghost.com\/cms\/\">http:\/\/motoghost.com\/cms\/<\/a><\/p>","button_text":""}},"template--16427970003128__995b3ef3-a555-43d2-b97b-76cdd877f3e9-text_block-3":{"type":"text_block","settings":{"link":"","title_text":"Arizona","text":"<p>GO AZ Motorcycles Flagstaff<br\/>1400. E Butler Ave.<br\/>Flagstaff, AZ, 86001 <br\/><a href=\"https:\/\/www.goazflagstaff.com\/\" title=\"https:\/\/www.goazflagstaff.com\/\">https:\/\/www.goazflagstaff.com\/<\/a><\/p>","button_text":""}},"6836c6c2-a84e-4ace-afd8-38f8967bf8d5":{"type":"text_block","settings":{"link":"","title_text":"British Columbia","text":"<p><strong>Mile Zero Motorsports<\/strong><br\/>13136 Thomas Rd<br\/>Ladysmith BC, V9G1L9<br\/>(250)-245-5414<br\/><a href=\"http:\/\/www.themilezero.com\/\" title=\"http:\/\/www.themilezero.com\/\">http:\/\/www.themilezero.com\/<\/a><\/p>","button_text":""}}},"block_order":["template--16427970003128__995b3ef3-a555-43d2-b97b-76cdd877f3e9-text_block-1","template--16427970003128__995b3ef3-a555-43d2-b97b-76cdd877f3e9-text_block-2","template--16427970003128__995b3ef3-a555-43d2-b97b-76cdd877f3e9-text_block-3","6836c6c2-a84e-4ace-afd8-38f8967bf8d5"],"disabled":true,"settings":{"title":"","image_height":"natural","desktop_height":450,"mobile_height":300,"align_text":"left","section_padding":"none"}},"2300bac2-9528-44fd-affe-daa75994927b":{"type":"editorial-columns","blocks":{"template--16427970003128__2300bac2-9528-44fd-affe-daa75994927b-text_block-1":{"type":"text_block","settings":{"link":"","title_text":"California","text":"<p><strong>Brown Motor Works<\/strong><br\/>885 W Mission Blvd<br\/>Ponoma CA, 91766<br\/>(909) 629-2132<br\/><a href=\"http:\/\/brownmotorworks.net\" title=\"http:\/\/brownmotorworks.net\">http:\/\/brownmotorworks.net<\/a><\/p>","button_text":""}},"template--16427970003128__2300bac2-9528-44fd-affe-daa75994927b-text_block-2":{"type":"text_block","settings":{"link":"","title_text":"California","text":"<p><strong>SF Moto<\/strong><br\/>275 8th St<br\/>San Fransisco CA 94103<br\/>(514) 404-9320<br\/><a href=\"http:\/\/www.sfmoto.com\" title=\"http:\/\/www.sfmoto.com\">http:\/\/www.sfmoto.com<\/a><\/p>","button_text":""}},"template--16427970003128__2300bac2-9528-44fd-affe-daa75994927b-text_block-3":{"type":"text_block","settings":{"link":"","title_text":"Colorado","text":"<p><strong>Performance Cycle Of Colorado<br\/><\/strong>375 S Fulton St<br\/>Centennial, CO 80112<br\/>(303) 744-2011<br\/><a href=\"http:\/\/performancecycle.com\/\">http:\/\/performancecycle.com\/<\/a><\/p>","button_text":""}},"ecb110a8-f477-43e9-9215-06ccefadaf7c":{"type":"text_block","settings":{"link":"","title_text":"Florida","text":"<p><strong>Power BMW Motorcycles of Palm Bay<br\/><\/strong>90 Interstate CT SE<br\/>Palm Bay, FL 32909<br\/>(321)-215-2065<br\/><a href=\"http:\/\/bmwmcofpalmbay.com\/\">http:\/\/bmwmcofpalmbay.com<\/a><\/p>","button_text":""}}},"block_order":["template--16427970003128__2300bac2-9528-44fd-affe-daa75994927b-text_block-1","template--16427970003128__2300bac2-9528-44fd-affe-daa75994927b-text_block-2","template--16427970003128__2300bac2-9528-44fd-affe-daa75994927b-text_block-3","ecb110a8-f477-43e9-9215-06ccefadaf7c"],"disabled":true,"settings":{"title":"","image_height":"natural","desktop_height":450,"mobile_height":300,"align_text":"left","section_padding":"none"}},"272de21a-56a6-4755-81d8-7a7298faa238":{"type":"editorial-columns","blocks":{"template--16427970003128__272de21a-56a6-4755-81d8-7a7298faa238-text_block-1":{"type":"text_block","settings":{"link":"","title_text":"Maryland","text":"<p><strong>Bob's BMW<\/strong><br\/>0720 GUILFORD RD<br\/>JESSUP, MD 20794<br\/>(301) 497-8949<br\/><a href=\"http:\/\/bobsbmw.com\/\">http:\/\/bobsbmw.com<\/a><\/p>","button_text":""}},"template--16427970003128__272de21a-56a6-4755-81d8-7a7298faa238-text_block-2":{"type":"text_block","settings":{"link":"","title_text":"Minnesota","text":"<p><strong>BMW Motorcycles of Richfield<\/strong><br\/>01 West 77th St. Suite 1<br\/>Richfield, MN 55423<br\/><a href=\"http:\/\/www.bmwmotorcyclesrichfield.com\/\">http:\/\/www.bmwmotorcyclesrichfield.com\/<\/a><\/p>","button_text":""}},"template--16427970003128__272de21a-56a6-4755-81d8-7a7298faa238-text_block-3":{"type":"text_block","settings":{"link":"","title_text":"Missouri","text":"<p><strong>Gateway BMW Motorcycles<br\/><\/strong>690 MASTERSON AVE STE 300<br\/>SAINT LOUIS, MO 63114<br\/>(314) 427-9090<br\/><a href=\"http:\/\/www.gatewaybmw.com\/\">http:\/\/www.gatewaybmw.com\/<\/a><\/p>","button_text":""}},"b551765c-7586-45d3-98e5-16ef7cda1243":{"type":"text_block","settings":{"link":"","title_text":"New Jersey","text":"<p><strong>Cross Country Powersports<br\/><\/strong>11 Middlesex Avenue<br\/>METUCHEN, NJ 08840<br\/>(732) 635-0094<br\/><a href=\"http:\/\/www.crosscountrypowersports.com\/\">http:\/\/www.crosscountrypowersports.com\/<\/a><\/p>","button_text":""}}},"block_order":["template--16427970003128__272de21a-56a6-4755-81d8-7a7298faa238-text_block-1","template--16427970003128__272de21a-56a6-4755-81d8-7a7298faa238-text_block-2","template--16427970003128__272de21a-56a6-4755-81d8-7a7298faa238-text_block-3","b551765c-7586-45d3-98e5-16ef7cda1243"],"disabled":true,"settings":{"title":"","image_height":"natural","desktop_height":450,"mobile_height":300,"align_text":"left","section_padding":"none"}},"f2596659-4a1e-4118-9e59-3859bf60d9a3":{"type":"editorial-columns","blocks":{"template--16427970003128__f2596659-4a1e-4118-9e59-3859bf60d9a3-text_block-1":{"type":"text_block","settings":{"link":"","title_text":"New Jersey","text":"<p><strong>Cross Country Cycle<br\/><\/strong>5 Route 17 South<br\/>Hasbrouck Heights, NJ 07604<br\/>(201)-288-0900<br\/><a href=\"https:\/\/www.crosscountrycycle.net\/\">https:\/\/www.crosscountrycycle.net\/<\/a><\/p>","button_text":""}},"template--16427970003128__f2596659-4a1e-4118-9e59-3859bf60d9a3-text_block-2":{"type":"text_block","settings":{"link":"","title_text":"Ohio","text":"<p><strong>Mid-Ohio Powersports<br\/><\/strong>94 HARCOURT RD<br\/>MOUNT VERNON  OH 43050<br\/>(740)-397-5272<br\/><a href=\"https:\/\/mid-ohio.com\/\" title=\"https:\/\/mid-ohio.com\/\">https:\/\/mid-ohio.com\/<\/a><\/p>","button_text":""}},"template--16427970003128__f2596659-4a1e-4118-9e59-3859bf60d9a3-text_block-3":{"type":"text_block","settings":{"link":"","title_text":"Ohio","text":"<p><strong>Motorcycles of Cleveland<\/strong><br\/>7315 N. Aurora Rd<br\/>Aurora OH 44202<br\/>(330)-562-5200<br\/>https:\/\/bmwmoc.com\/<\/p>","button_text":""}},"4026b9ee-3bd8-4cdd-b1a3-71d4edc17618":{"type":"text_block","settings":{"link":"","title_text":"Ontario","text":"<p><strong>Dualsport Plus<\/strong><br\/>81 West street<br\/>St Brantford, ON N3R7C5<br\/>(888)-990-9013<br\/><a href=\"http:\/\/www.dualsportplus.com\/\">www.dualsportplus.com<\/a><\/p>","button_text":""}}},"block_order":["template--16427970003128__f2596659-4a1e-4118-9e59-3859bf60d9a3-text_block-1","template--16427970003128__f2596659-4a1e-4118-9e59-3859bf60d9a3-text_block-2","template--16427970003128__f2596659-4a1e-4118-9e59-3859bf60d9a3-text_block-3","4026b9ee-3bd8-4cdd-b1a3-71d4edc17618"],"disabled":true,"settings":{"title":"","image_height":"natural","desktop_height":450,"mobile_height":300,"align_text":"left","section_padding":"none"}},"e61f5b2f-1a03-4eb3-b0ae-efdc210e1942":{"type":"editorial-columns","blocks":{"template--16427970003128__e61f5b2f-1a03-4eb3-b0ae-efdc210e1942-text_block-1":{"type":"text_block","settings":{"link":"","title_text":"Quebec","text":"<p><strong>Gabriel Moto B Montréal<\/strong><br\/>695 rue St-Jacques Ouest<br\/>Montreal, QC H4B1V3<br\/>(514)-712-7777<br\/><a href=\"http:\/\/www.gabrielbmwmoto.ca\/\">www.gabrielbmwmoto.ca<\/a>  <\/p>","button_text":""}},"template--16427970003128__e61f5b2f-1a03-4eb3-b0ae-efdc210e1942-text_block-2":{"type":"text_block","settings":{"link":"","title_text":"Quebec","text":"<p><strong>Performance NC Sherbrooke<\/strong><br\/>9460 Boulevard Bourque<br\/>Sherbrooke, QC, J1N0G2<br\/>(855)-821-3595<br\/><a href=\"https:\/\/performancenc.ca\" title=\"https:\/\/performancenc.ca\">https:\/\/performancenc.ca<\/a><\/p>","button_text":""}},"template--16427970003128__e61f5b2f-1a03-4eb3-b0ae-efdc210e1942-text_block-3":{"type":"text_block","settings":{"link":"","title_text":"Rhode Island","text":"<p><strong>Twisted Throttle<\/strong><br\/>570 Nooseneck Hill Road<br\/>Exeter, RI 02822<br\/>(855) 255-5550<br\/><a href=\"https:\/\/www.twistedthrottle.com\/\">https:\/\/www.twistedthrottle.com\/<\/a><\/p>","button_text":""}},"3ce76931-5638-4003-ab18-cea9dc129f14":{"type":"text_block","settings":{"link":"","title_text":"Texas","text":"<p><strong>AF1 Racing<br\/><\/strong>900 N Interstate 35<br\/>Austin, TX, 78753<br\/>(512) 459-3966<br\/><a href=\"http:\/\/af1racing.com\/\">http:\/\/af1racing.com<\/a><\/p>","button_text":""}}},"block_order":["template--16427970003128__e61f5b2f-1a03-4eb3-b0ae-efdc210e1942-text_block-1","template--16427970003128__e61f5b2f-1a03-4eb3-b0ae-efdc210e1942-text_block-2","template--16427970003128__e61f5b2f-1a03-4eb3-b0ae-efdc210e1942-text_block-3","3ce76931-5638-4003-ab18-cea9dc129f14"],"disabled":true,"settings":{"title":"","image_height":"natural","desktop_height":450,"mobile_height":300,"align_text":"left","section_padding":"none"}},"9211a12d-2909-47ea-b914-f722b2f8165c":{"type":"editorial-columns","blocks":{"template--16427970003128__9211a12d-2909-47ea-b914-f722b2f8165c-text_block-1":{"type":"text_block","settings":{"link":"","title_text":"Virginia","text":"<p><strong>Morton's BMW Motorcycles<\/strong><br\/>099A Jefferson Davis Highway<br\/>Fredericksburg, Virginia 22408<br\/>(540) 891-9844<br\/><a href=\"http:\/\/www.mortonsbmw.com\/\">http:\/\/www.mortonsbmw.com\/<\/a><\/p>","button_text":""}},"template--16427970003128__9211a12d-2909-47ea-b914-f722b2f8165c-text_block-2":{"type":"text_block","settings":{"link":"","title_text":"Your Store Here","text":"<p><strong>Want to be featured? <br\/><\/strong>Fill out the form above <br\/>or connected with your Rep at<br\/>(888)-994-4484<br\/><a href=\"https:\/\/www.twisteddistributing.com\/\" title=\"https:\/\/www.twisteddistributing.com\/\">https:\/\/www.twisteddistributing.com\/<\/a><\/p>","button_text":""}},"template--16427970003128__9211a12d-2909-47ea-b914-f722b2f8165c-text_block-3":{"type":"text_block","settings":{"link":"","title_text":"","text":"","button_text":""}},"20976964-4729-4d22-a85b-bfa5cba8270e":{"type":"text_block","settings":{"link":"","title_text":"","text":"","button_text":""}}},"block_order":["template--16427970003128__9211a12d-2909-47ea-b914-f722b2f8165c-text_block-1","template--16427970003128__9211a12d-2909-47ea-b914-f722b2f8165c-text_block-2","template--16427970003128__9211a12d-2909-47ea-b914-f722b2f8165c-text_block-3","20976964-4729-4d22-a85b-bfa5cba8270e"],"disabled":true,"settings":{"title":"","image_height":"natural","desktop_height":450,"mobile_height":300,"align_text":"left","section_padding":"none"}},"abbb7a8c-1c28-457b-a3ba-76762653ad0d":{"type":"page-custom-DataDim-template","blocks":{"3040d128-0f84-4eba-b314-ac3f826ad157":{"type":"image_text_overlay","disabled":true,"settings":{"full_width":true,"image":"shopify:\/\/shop_images\/Distributor_Map_2000x600-01_a2090689-6b81-40d1-945e-1ac09a0b7fee.jpg","image_height":600,"heading":"","hidden_text":"","link":"","button_text":"View Product","heading_text_size":28,"hidden_text_size":14,"heading_color":"#ffffff","text_color":"#bdbdbd","button_text_color":"#ffffff","button_color":"#000000","section_padding":"both"}},"8d5e21a3-fad4-409c-bc8a-791674ad1e88":{"type":"image_text_overlay","settings":{"full_width":true,"image":"shopify:\/\/shop_images\/ADV_Ender_Bright_Sky_c6a65700-882d-4a23-a437-3116bc10c433.jpg","image_height":500,"heading":"","hidden_text":"","link":"","button_text":"","heading_text_size":28,"hidden_text_size":18,"heading_color":"#000000","text_color":"#000000","button_text_color":"#ffffff","button_color":"#000000","section_padding":"top"}}},"block_order":["3040d128-0f84-4eba-b314-ac3f826ad157","8d5e21a3-fad4-409c-bc8a-791674ad1e88"],"settings":{}},"d31c151d-d1d9-47de-9f23-17d1f419ab2e":{"type":"editorial-columns","blocks":{"template--16427970003128__d31c151d-d1d9-47de-9f23-17d1f419ab2e-text_block-1":{"type":"text_block","settings":{"link":"","title_text":"Australia","text":"<p><strong>Whites Powersports<\/strong> <br\/><a href=\"http:\/\/www.whitespowersports.com\/\">http:\/\/www.whitespowersports.com\/<\/a><\/p>","button_text":""}},"template--16427970003128__d31c151d-d1d9-47de-9f23-17d1f419ab2e-text_block-2":{"type":"text_block","settings":{"link":"","title_text":"Benelux","text":"<p><strong>Bihr - Netherlands <br\/><\/strong><a href=\"https:\/\/www.bihr.eu\/\" title=\"https:\/\/www.bihr.eu\/\">https:\/\/www.bihr.eu\/<\/a><\/p>","button_text":""}},"template--16427970003128__d31c151d-d1d9-47de-9f23-17d1f419ab2e-text_block-3":{"type":"text_block","settings":{"link":"","title_text":"Canada","text":"<p><strong>Twisted Distributing CA<\/strong><br\/><a href=\"https:\/\/www.twisteddistributing.ca\/\" title=\"https:\/\/www.twisteddistributing.ca\/\">https:\/\/www.twisteddistributing.ca\/<\/a><\/p>","button_text":""}},"8da98872-b158-4cf2-a455-7283e35e835d":{"type":"text_block","settings":{"link":"","title_text":"France","text":"<p><strong>Bihr - France<br\/><\/strong><a href=\"https:\/\/www.bihr.eu\/\" title=\"https:\/\/www.bihr.eu\/\">https:\/\/www.bihr.eu\/<\/a><br\/><\/p>","button_text":""}}},"block_order":["template--16427970003128__d31c151d-d1d9-47de-9f23-17d1f419ab2e-text_block-1","template--16427970003128__d31c151d-d1d9-47de-9f23-17d1f419ab2e-text_block-2","template--16427970003128__d31c151d-d1d9-47de-9f23-17d1f419ab2e-text_block-3","8da98872-b158-4cf2-a455-7283e35e835d"],"disabled":true,"settings":{"title":"Official Distributors","image_height":"natural","desktop_height":450,"mobile_height":300,"align_text":"left","section_padding":"both"}},"c71ec060-fa78-40ce-8d06-6faee182b131":{"type":"editorial-columns","blocks":{"template--16427970003128__c71ec060-fa78-40ce-8d06-6faee182b131-text_block-1":{"type":"text_block","settings":{"link":"","title_text":"India","text":"<p><strong>Big Bad Bikes<\/strong><br\/><a href=\"https:\/\/bigbadbikes.com\/\">https:\/\/bigbadbikes.com\/<\/a><\/p>","button_text":""}},"template--16427970003128__c71ec060-fa78-40ce-8d06-6faee182b131-text_block-2":{"type":"text_block","settings":{"link":"","title_text":"Japan","text":"<p><strong>Pro-Tecta Corp<br\/><\/strong><a href=\"http:\/\/www.pro-tecta.com\/\" title=\"http:\/\/www.pro-tecta.com\/\">http:\/\/www.pro-tecta.com\/<\/a><\/p>","button_text":""}},"template--16427970003128__c71ec060-fa78-40ce-8d06-6faee182b131-text_block-3":{"type":"text_block","settings":{"link":"","title_text":"Mexico","text":"<p><strong>ACC Parts<br\/><\/strong><a href=\"http:\/\/www.ACC-Parts.com\" title=\"http:\/\/www.ACC-Parts.com\">http:\/\/www.acc-parts.com<\/a><\/p>","button_text":""}},"327a0ce9-0e7b-427d-ad1b-687f15dd64c6":{"type":"text_block","settings":{"link":"","title_text":"New Zealand","text":"<p><strong>Whites Powersports <br\/><\/strong><a href=\"http:\/\/www.whitespowersports.com\/\">http:\/\/www.whitespowersports.com\/<\/a><\/p>","button_text":""}}},"block_order":["template--16427970003128__c71ec060-fa78-40ce-8d06-6faee182b131-text_block-1","template--16427970003128__c71ec060-fa78-40ce-8d06-6faee182b131-text_block-2","template--16427970003128__c71ec060-fa78-40ce-8d06-6faee182b131-text_block-3","327a0ce9-0e7b-427d-ad1b-687f15dd64c6"],"disabled":true,"settings":{"title":"","image_height":"natural","desktop_height":450,"mobile_height":300,"align_text":"left","section_padding":"both"}},"0154ac85-f24d-46d5-a7ee-3dd67beac47f":{"type":"editorial-columns","blocks":{"template--16427970003128__0154ac85-f24d-46d5-a7ee-3dd67beac47f-text_block-1":{"type":"text_block","settings":{"link":"","title_text":"Spain","text":"<p>Totimport<br\/> <a href=\"https:\/\/www.totimport.com\/\" target=\"_blank\">https:\/\/www.totimport.com\/<\/a><br\/><\/p>","button_text":""}},"template--16427970003128__0154ac85-f24d-46d5-a7ee-3dd67beac47f-text_block-2":{"type":"text_block","settings":{"link":"","title_text":"United Arab Emirates","text":"<p><strong>Oldtimer Motorcycles<br\/><\/strong><a href=\"https:\/\/www.facebook.com\/oldtimermiddleeast\/\" target=\"_blank\" title=\"https:\/\/www.facebook.com\/oldtimermiddleeast\/\">View Website<\/a><br\/><\/p>","button_text":""}},"template--16427970003128__0154ac85-f24d-46d5-a7ee-3dd67beac47f-text_block-3":{"type":"text_block","settings":{"link":"","title_text":"United Kingdom","text":"<p><strong>R&G Racing<br\/><\/strong><a href=\"http:\/\/www.rg-racing.com\/\" title=\"http:\/\/www.rg-racing.com\/\">http:\/\/www.rg-racing.com\/<\/a><br\/><\/p>","button_text":""}},"5c1af3e4-4302-489e-b7da-3f33ab622e64":{"type":"text_block","settings":{"link":"","title_text":"United States","text":"<p><strong>Twisted Distributing USA<br\/><\/strong><a href=\"https:\/\/www.twisteddistributing.com\/\" title=\"https:\/\/www.twisteddistributing.com\/\">https:\/\/www.twisteddistributing.com\/<\/a><\/p>","button_text":""}}},"block_order":["template--16427970003128__0154ac85-f24d-46d5-a7ee-3dd67beac47f-text_block-1","template--16427970003128__0154ac85-f24d-46d5-a7ee-3dd67beac47f-text_block-2","template--16427970003128__0154ac85-f24d-46d5-a7ee-3dd67beac47f-text_block-3","5c1af3e4-4302-489e-b7da-3f33ab622e64"],"disabled":true,"settings":{"title":"","image_height":"natural","desktop_height":450,"mobile_height":300,"align_text":"left","section_padding":"both"}},"22199a26-fc9e-444f-8355-f2169fb48d1f":{"type":"editorial-columns","blocks":{"template--16427970003128__22199a26-fc9e-444f-8355-f2169fb48d1f-text_block-1":{"type":"text_block","settings":{"link":"","title_text":"Switzerland","text":"<p><strong>Bihr - France<br\/><\/strong><a href=\"https:\/\/www.bihr.eu\/\" title=\"https:\/\/www.bihr.eu\/\">https:\/\/www.bihr.eu\/<\/a><br\/><\/p>","button_text":""}},"template--16427970003128__22199a26-fc9e-444f-8355-f2169fb48d1f-text_block-2":{"type":"text_block","settings":{"link":"","title_text":"Norway","text":"<p><strong>Spare Parts Sevice<br\/><\/strong><a href=\"https:\/\/www.sps.no\/\" title=\"https:\/\/www.sps.no\/\">https:\/\/www.sps.no\/<\/a><\/p>","button_text":""}},"template--16427970003128__22199a26-fc9e-444f-8355-f2169fb48d1f-text_block-3":{"type":"text_block","settings":{"link":"","title_text":"Colombia","text":"<p>InduGuimm S.A.S. DBA En Moto<br\/><a href=\"https:\/\/enmoto.co\/\" target=\"_blank\">https:\/\/enmoto.co\/<\/a><\/p>","button_text":""}},"265f4497-972d-4ce6-ba49-57a3487d0e6a":{"type":"text_block","settings":{"link":"","title_text":"Russia","text":"<p>WikiMoto<br\/><a href=\"https:\/\/wikimoto.ru\/\" target=\"_blank\">https:\/\/wikimoto.ru\/<\/a><\/p>","button_text":""}}},"block_order":["template--16427970003128__22199a26-fc9e-444f-8355-f2169fb48d1f-text_block-1","template--16427970003128__22199a26-fc9e-444f-8355-f2169fb48d1f-text_block-2","template--16427970003128__22199a26-fc9e-444f-8355-f2169fb48d1f-text_block-3","265f4497-972d-4ce6-ba49-57a3487d0e6a"],"disabled":true,"settings":{"title":"","image_height":"natural","desktop_height":450,"mobile_height":300,"align_text":"left","section_padding":"both"}},"60fb77ed-b1c5-47d8-9bbb-feff6fd6b6e0":{"type":"editorial-columns","blocks":{"template--16427970003128__60fb77ed-b1c5-47d8-9bbb-feff6fd6b6e0-text_block-1":{"type":"text_block","settings":{"link":"","title_text":"Saudi Arabia","text":"<p><strong>Oldtimer Motorcycles<br\/><\/strong><a href=\"https:\/\/www.facebook.com\/oldtimermiddleeast\/\" target=\"_blank\" title=\"https:\/\/www.facebook.com\/oldtimermiddleeast\/\">View Website<\/a><\/p>","button_text":""}},"template--16427970003128__60fb77ed-b1c5-47d8-9bbb-feff6fd6b6e0-text_block-2":{"type":"text_block","settings":{"link":"","title_text":"Bahrein","text":"<p><strong>Oldtimer Motorcycles<br\/><\/strong><a href=\"https:\/\/www.facebook.com\/oldtimermiddleeast\/\" target=\"_blank\" title=\"https:\/\/www.facebook.com\/oldtimermiddleeast\/\">View Website<\/a><\/p>","button_text":""}},"template--16427970003128__60fb77ed-b1c5-47d8-9bbb-feff6fd6b6e0-text_block-3":{"type":"text_block","settings":{"link":"","title_text":"Qatar","text":"<p><strong>Oldtimer Motorcycles<br\/><\/strong><a href=\"https:\/\/www.facebook.com\/oldtimermiddleeast\/\" target=\"_blank\" title=\"https:\/\/www.facebook.com\/oldtimermiddleeast\/\">View Website<\/a><\/p>","button_text":""}},"5f5c1af5-bbd6-486c-9dd1-78eda11a323a":{"type":"text_block","settings":{"link":"","title_text":"Koweit","text":"<p><strong>Oldtimer Motorcycles<br\/><\/strong><a href=\"https:\/\/www.facebook.com\/oldtimermiddleeast\/\" target=\"_blank\" title=\"https:\/\/www.facebook.com\/oldtimermiddleeast\/\">View Website<\/a><\/p>","button_text":""}}},"block_order":["template--16427970003128__60fb77ed-b1c5-47d8-9bbb-feff6fd6b6e0-text_block-1","template--16427970003128__60fb77ed-b1c5-47d8-9bbb-feff6fd6b6e0-text_block-2","template--16427970003128__60fb77ed-b1c5-47d8-9bbb-feff6fd6b6e0-text_block-3","5f5c1af5-bbd6-486c-9dd1-78eda11a323a"],"disabled":true,"settings":{"title":"","image_height":"natural","desktop_height":450,"mobile_height":300,"align_text":"left","section_padding":"both"}},"d4d77d60-a718-4e31-8bf9-30b532f88df4":{"type":"editorial-columns","blocks":{"template--16427970003128__d4d77d60-a718-4e31-8bf9-30b532f88df4-text_block-1":{"type":"text_block","settings":{"link":"","title_text":"Poland","text":"<p><strong>MEFO Sport Polska<br\/><\/strong><a href=\"https:\/\/sklep.mefo.pl\" target=\"_blank\" title=\"https:\/\/sklep.mefo.pl\">sklep.mefo.pl<\/a><\/p>","button_text":""}},"template--16427970003128__d4d77d60-a718-4e31-8bf9-30b532f88df4-text_block-2":{"type":"text_block","settings":{"link":"","title_text":"","text":"","button_text":""}},"template--16427970003128__d4d77d60-a718-4e31-8bf9-30b532f88df4-text_block-3":{"type":"text_block","settings":{"link":"","title_text":"","text":"","button_text":""}},"ebded147-65ec-4e6e-b717-ee7f053a3430":{"type":"text_block","settings":{"link":"","title_text":"","text":"","button_text":""}}},"block_order":["template--16427970003128__d4d77d60-a718-4e31-8bf9-30b532f88df4-text_block-1","template--16427970003128__d4d77d60-a718-4e31-8bf9-30b532f88df4-text_block-2","template--16427970003128__d4d77d60-a718-4e31-8bf9-30b532f88df4-text_block-3","ebded147-65ec-4e6e-b717-ee7f053a3430"],"disabled":true,"settings":{"title":"","image_height":"natural","desktop_height":450,"mobile_height":300,"align_text":"left","section_padding":"both"}},"224815b0-1374-4fc2-9830-529d87860f8e":{"type":"editorial-columns","blocks":{"template--16427970003128__224815b0-1374-4fc2-9830-529d87860f8e-text_block-1":{"type":"text_block","settings":{"link":"https:\/\/www.adventuremoto.com.au\/","title_text":"Australia","text":"<p>Adventure Moto<br\/><a href=\"https:\/\/www.adventuremoto.com.au\/\" title=\"https:\/\/www.adventuremoto.com.au\/\">https:\/\/www.adventuremoto.com.au\/<\/a><\/p>","button_text":""}},"template--16427970003128__224815b0-1374-4fc2-9830-529d87860f8e-text_block-2":{"type":"text_block","settings":{"link":"","title_text":"Chile","text":"<p><strong>RCC SPA<\/strong><br\/><a href=\"https:\/\/motoss.cl\" title=\"https:\/\/motoss.cl\">https:\/\/motoss.cl<\/a><\/p>","button_text":""}},"template--16427970003128__224815b0-1374-4fc2-9830-529d87860f8e-text_block-3":{"type":"text_block","settings":{"link":"","title_text":"Czech Republic","text":"<p>MotoElectrics<br\/>http:\/\/www.motoelectrics.cz\/<\/p>","button_text":""}},"9179928a-4b73-4cb2-a6f0-9d696a1066ae":{"type":"text_block","settings":{"link":"","title_text":"Costa Rica, Nicaragua, Honduras","text":"<p>MS Motospot CentroAmerica<br\/><a href=\"https:\/\/motospotca.com\/\" target=\"_blank\">https:\/\/motospotca.com\/<\/a><\/p>","button_text":""}}},"block_order":["template--16427970003128__224815b0-1374-4fc2-9830-529d87860f8e-text_block-1","template--16427970003128__224815b0-1374-4fc2-9830-529d87860f8e-text_block-2","template--16427970003128__224815b0-1374-4fc2-9830-529d87860f8e-text_block-3","9179928a-4b73-4cb2-a6f0-9d696a1066ae"],"disabled":true,"settings":{"title":"Featured International Dealers","image_height":"natural","desktop_height":450,"mobile_height":300,"align_text":"left","section_padding":"both"}},"b94bdb77-fcf4-4445-8a21-03b2272b4cec":{"type":"editorial-columns","blocks":{"template--16427970003128__b94bdb77-fcf4-4445-8a21-03b2272b4cec-text_block-1":{"type":"text_block","settings":{"link":"","title_text":"China","text":"<p><strong>OTJ Moto<br\/><\/strong><a href=\"https:\/\/otjmoto.taobao.com\/\" title=\"https:\/\/otjmoto.taobao.com\/\">https:\/\/otjmoto.taobao.com\/<\/a><\/p><p><\/p>","button_text":""}},"template--16427970003128__b94bdb77-fcf4-4445-8a21-03b2272b4cec-text_block-2":{"type":"text_block","settings":{"link":"","title_text":"Colombia","text":"<p><strong>Motos & Servitecas de Colombia<br\/><\/strong><a href=\"http:\/\/www.motosyservitecas.com\/\" title=\"http:\/\/www.motosyservitecas.com\/\">http:\/\/www.motosyservitecas.com\/<\/a><br\/><\/p>","button_text":""}},"template--16427970003128__b94bdb77-fcf4-4445-8a21-03b2272b4cec-text_block-3":{"type":"text_block","settings":{"link":"","title_text":"Ecuador","text":"<p><strong>Euromoto<\/strong><br\/><a href=\"mailto:info@euromotoec.com\" title=\"mailto:info@euromotoec.com\">info@euromotoec.com<\/a><\/p>","button_text":""}},"5b9bd895-d201-4384-8c40-7f680ab5f428":{"type":"text_block","settings":{"link":"","title_text":"El Salvador","text":"<p><strong>Drift El Salvador<br\/><\/strong><a href=\"mailto:driftelsalvador@hotmail.com\">driftelsalvador@hotmail.com<\/a><\/p>","button_text":""}}},"block_order":["template--16427970003128__b94bdb77-fcf4-4445-8a21-03b2272b4cec-text_block-1","template--16427970003128__b94bdb77-fcf4-4445-8a21-03b2272b4cec-text_block-2","template--16427970003128__b94bdb77-fcf4-4445-8a21-03b2272b4cec-text_block-3","5b9bd895-d201-4384-8c40-7f680ab5f428"],"disabled":true,"settings":{"title":"","image_height":"natural","desktop_height":450,"mobile_height":300,"align_text":"left","section_padding":"both"}},"16b233fb-ee58-4bf7-87d3-b4099738abb6":{"type":"editorial-columns","blocks":{"template--16427970003128__16b233fb-ee58-4bf7-87d3-b4099738abb6-text_block-1":{"type":"text_block","settings":{"link":"","title_text":"Germany","text":"<p><strong>Cali Parts Cycles<br\/><\/strong>socalparts@mail.com<br\/><br\/><\/p>","button_text":""}},"template--16427970003128__16b233fb-ee58-4bf7-87d3-b4099738abb6-text_block-2":{"type":"text_block","settings":{"link":"","title_text":"Guatemala","text":"<p><strong>Motopolis<br\/><\/strong><a href=\"http:\/\/motopolis.com.gt\/\" title=\"http:\/\/motopolis.com.gt\/\">http:\/\/motopolis.com.gt\/<\/a><\/p>","button_text":""}},"template--16427970003128__16b233fb-ee58-4bf7-87d3-b4099738abb6-text_block-3":{"type":"text_block","settings":{"link":"","title_text":"Malaysia","text":"<p><strong>Sunny Cycle<br\/><\/strong><a href=\"https:\/\/www.facebook.com\/sunnycycle\/\" title=\"https:\/\/www.facebook.com\/sunnycycle\/\">https:\/\/www.facebook.com\/sunnycycle\/<\/a><\/p>","button_text":""}},"20a9f03a-a27d-4d89-9622-1fa284c27488":{"type":"text_block","settings":{"link":"","title_text":"Portugal","text":"<p><strong>In-Parts<\/strong><br\/><a href=\"http:\/\/www.in-parts.com\">www.in-parts.com<\/a><br\/><\/p>","button_text":""}}},"block_order":["template--16427970003128__16b233fb-ee58-4bf7-87d3-b4099738abb6-text_block-1","template--16427970003128__16b233fb-ee58-4bf7-87d3-b4099738abb6-text_block-2","template--16427970003128__16b233fb-ee58-4bf7-87d3-b4099738abb6-text_block-3","20a9f03a-a27d-4d89-9622-1fa284c27488"],"disabled":true,"settings":{"title":"","image_height":"natural","desktop_height":450,"mobile_height":300,"align_text":"left","section_padding":"both"}},"e143743e-729d-4352-bc7a-898ae7500bfd":{"type":"editorial-columns","blocks":{"template--16427970003128__e143743e-729d-4352-bc7a-898ae7500bfd-text_block-1":{"type":"text_block","settings":{"link":"","title_text":"Philippines","text":"<p><strong>Motohub<br\/><\/strong><a href=\"http:\/\/www.motohubph.com\/\" title=\"http:\/\/www.motohubph.com\/\">http:\/\/www.motohubph.com\/<\/a><br\/><\/p>","button_text":""}},"template--16427970003128__e143743e-729d-4352-bc7a-898ae7500bfd-text_block-2":{"type":"text_block","settings":{"link":"","title_text":"Philippines","text":"<p><strong>ProMoto Trading<br\/><\/strong><a href=\"https:\/\/www.facebook.com\/promotomakati\" title=\"https:\/\/www.facebook.com\/promotomakati\">view website<\/a><\/p>","button_text":""}},"template--16427970003128__e143743e-729d-4352-bc7a-898ae7500bfd-text_block-3":{"type":"text_block","settings":{"link":"","title_text":"Philippines","text":"<p><strong>Motoscoot<\/strong><br\/><a href=\"https:\/\/www.facebook.com\/motoscootph\/\" title=\"https:\/\/www.facebook.com\/motoscootph\/\">https:\/\/www.facebook.com\/motoscootph\/<\/a><\/p>","button_text":""}},"ec6c4e46-b3fd-40b8-91d8-4f1dba16ab63":{"type":"text_block","settings":{"link":"","title_text":"Philippines","text":"<p><strong>Big Bike Tech<br\/><\/strong>https:\/\/bigbike.tech\/<br\/><\/p>","button_text":""}}},"block_order":["template--16427970003128__e143743e-729d-4352-bc7a-898ae7500bfd-text_block-1","template--16427970003128__e143743e-729d-4352-bc7a-898ae7500bfd-text_block-2","template--16427970003128__e143743e-729d-4352-bc7a-898ae7500bfd-text_block-3","ec6c4e46-b3fd-40b8-91d8-4f1dba16ab63"],"disabled":true,"settings":{"title":"","image_height":"natural","desktop_height":450,"mobile_height":300,"align_text":"left","section_padding":"both"}},"669a4369-94cb-4e83-b52f-89949f47c22b":{"type":"editorial-columns","blocks":{"template--16427970003128__669a4369-94cb-4e83-b52f-89949f47c22b-text_block-1":{"type":"text_block","settings":{"link":"","title_text":"Philippines","text":"<p>MPH2.0 Motorsports Inc.<br\/><a href=\"https:\/\/www.facebook.com\/mphmotorsportsinc\/\" target=\"_blank\">View Website<\/a><\/p>","button_text":""}},"template--16427970003128__669a4369-94cb-4e83-b52f-89949f47c22b-text_block-2":{"type":"text_block","settings":{"link":"","title_text":"Turkey","text":"<p><strong>Oguz Motor<br\/><\/strong><a href=\"https:\/\/www.facebook.com\/oguzmotorantalya\/\" target=\"_blank\" title=\"https:\/\/www.facebook.com\/oguzmotorantalya\/\">https:\/\/www.facebook.com\/oguzmotorantalya\/<\/a><\/p>","button_text":""}},"template--16427970003128__669a4369-94cb-4e83-b52f-89949f47c22b-text_block-3":{"type":"text_block","settings":{"link":"","title_text":"Portugal","text":"<p>Portugal<\/p>","button_text":""}},"5b17e58c-b13d-4030-ab98-558beb4b1203":{"type":"text_block","settings":{"link":"","title_text":"Singapore","text":"<p><strong>Regina Specialties <br\/><\/strong><a href=\"http:\/\/www.reginaspecialties.com.sg\/\" title=\"http:\/\/www.reginaspecialties.com.sg\">www.reginaspecialties.com.sg<\/a><\/p>","button_text":""}}},"block_order":["template--16427970003128__669a4369-94cb-4e83-b52f-89949f47c22b-text_block-1","template--16427970003128__669a4369-94cb-4e83-b52f-89949f47c22b-text_block-2","template--16427970003128__669a4369-94cb-4e83-b52f-89949f47c22b-text_block-3","5b17e58c-b13d-4030-ab98-558beb4b1203"],"disabled":true,"settings":{"title":"","image_height":"natural","desktop_height":450,"mobile_height":300,"align_text":"left","section_padding":"both"}},"b11e40c1-b710-4c77-8045-19c3c03f7887":{"type":"editorial-columns","blocks":{"template--16427970003128__b11e40c1-b710-4c77-8045-19c3c03f7887-text_block-1":{"type":"text_block","settings":{"link":"","title_text":"Thailand","text":"<p><strong>TwoWheels Distributor CO<br\/><\/strong><a href=\"https:\/\/www.facebook.com\/2WTshop\/\" target=\"_blank\" title=\"https:\/\/www.facebook.com\/2WTshop\/\">https:\/\/www.facebook.com\/2WTshop\/<\/a><\/p>","button_text":""}},"template--16427970003128__b11e40c1-b710-4c77-8045-19c3c03f7887-text_block-2":{"type":"text_block","settings":{"link":"","title_text":"Taiwan","text":"<p><strong>Typhoon Protector<br\/><\/strong><a href=\"https:\/\/www.ruten.com.tw\/store\/mumu0915716158\/\" target=\"_blank\" title=\"https:\/\/www.ruten.com.tw\/store\/mumu0915716158\/\">View Website<\/a><\/p>","button_text":""}},"template--16427970003128__b11e40c1-b710-4c77-8045-19c3c03f7887-text_block-3":{"type":"text_block","settings":{"link":"","title_text":"Turkey","text":"<p><strong>Hepsimoto<br\/><\/strong><a href=\"https:\/\/www.hepsimoto.com\/\" target=\"_blank\" title=\"https:\/\/www.hepsimoto.com\/\">https:\/\/www.hepsimoto.com\/<\/a><\/p>","button_text":""}},"c612d503-48bb-4fb6-9af4-66ace8528194":{"type":"text_block","settings":{"link":"","title_text":"Ukraine","text":"<p><strong>So Rough Motorheads<br\/><\/strong><a href=\"http:\/\/srm.com.ua\/\">srm.com.ua<\/a><\/p>","button_text":""}}},"block_order":["template--16427970003128__b11e40c1-b710-4c77-8045-19c3c03f7887-text_block-1","template--16427970003128__b11e40c1-b710-4c77-8045-19c3c03f7887-text_block-2","template--16427970003128__b11e40c1-b710-4c77-8045-19c3c03f7887-text_block-3","c612d503-48bb-4fb6-9af4-66ace8528194"],"disabled":true,"settings":{"title":"","image_height":"natural","desktop_height":450,"mobile_height":300,"align_text":"left","section_padding":"both"}},"241bea62-67a3-4d75-9545-e6a041376c05":{"type":"editorial-columns","blocks":{"template--16427970003128__241bea62-67a3-4d75-9545-e6a041376c05-text_block-1":{"type":"text_block","settings":{"link":"","title_text":"Ukraine","text":"<p><strong>Motorrads<\/strong><br\/><a href=\"https:\/\/motorrads.com.ua\/\">https:\/\/motorrads.com.ua\/<\/a><\/p>","button_text":""}},"template--16427970003128__241bea62-67a3-4d75-9545-e6a041376c05-text_block-2":{"type":"text_block","settings":{"link":"","title_text":"Venezuela","text":"<p><strong>La Ideal World<\/strong><br\/><a href=\"mailto:charles@laidealworld.com.ve\" target=\"_blank\">charles@laidealworld.com.ve<\/a><\/p><p><br\/><br\/><\/p>","button_text":""}},"template--16427970003128__241bea62-67a3-4d75-9545-e6a041376c05-text_block-3":{"type":"text_block","settings":{"link":"","title_text":"Vietnam","text":"<p><strong>TAN QUANG COMPANY<\/strong><a href=\"https:\/\/www.facebook.com\/Denali-Electronics-Dealer-Vn-106148048567898\/\" target=\"_blank\"><br\/>View Website<\/a><\/p>","button_text":""}},"2c22f0af-7a68-464b-885a-a8fc377bb318":{"type":"text_block","settings":{"link":"","title_text":"Denmark","text":"<p><strong>MPR Grej v\/Morten Risum<\/strong><br\/><a href=\"http:\/\/adventuregrej.dk\/\" title=\"http:\/\/adventuregrej.dk\/\">http:\/\/adventuregrej.dk\/<\/a><\/p>","button_text":""}}},"block_order":["template--16427970003128__241bea62-67a3-4d75-9545-e6a041376c05-text_block-1","template--16427970003128__241bea62-67a3-4d75-9545-e6a041376c05-text_block-2","template--16427970003128__241bea62-67a3-4d75-9545-e6a041376c05-text_block-3","2c22f0af-7a68-464b-885a-a8fc377bb318"],"disabled":true,"settings":{"title":"","image_height":"natural","desktop_height":450,"mobile_height":300,"align_text":"left","section_padding":"both"}},"c3046b0e-777d-4973-8d1b-4c9e7bd069e9":{"type":"editorial-columns","blocks":{"template--16427970003128__c3046b0e-777d-4973-8d1b-4c9e7bd069e9-text_block-1":{"type":"text_block","settings":{"link":"","title_text":"Ukraine","text":"<p><strong>Brand Park<br\/><\/strong><a href=\"https:\/\/motorrads.com.ua\/ \" target=\"_blank\" title=\"https:\/\/motorrads.com.ua\/ \">https:\/\/motorrads.com.ua\/ <\/a><\/p>","button_text":""}},"template--16427970003128__c3046b0e-777d-4973-8d1b-4c9e7bd069e9-text_block-2":{"type":"text_block","settings":{"link":"","title_text":"Portugal","text":"<p><strong>In-Parts<br\/><\/strong><a href=\"https:\/\/www.in-parts.com\" target=\"_blank\" title=\"https:\/\/www.in-parts.com\">www.in-parts.com<\/a><\/p>","button_text":""}},"template--16427970003128__c3046b0e-777d-4973-8d1b-4c9e7bd069e9-text_block-3":{"type":"text_block","settings":{"link":"","title_text":"Lebanon","text":"<p><strong>Moto Trails Lebanon<br\/><\/strong>mototrailslebanon@gmail.com<\/p>","button_text":""}},"5009838a-920c-41bb-841b-9aaa0cae592f":{"type":"text_block","settings":{"link":"","title_text":"Latvia","text":"<p><strong>Motorbike LV<\/strong><br\/><a href=\"https:\/\/motorbike.lv\" target=\"_blank\" title=\"https:\/\/motorbike.lv\">https:\/\/motorbike.lv<\/a><\/p>","button_text":""}}},"block_order":["template--16427970003128__c3046b0e-777d-4973-8d1b-4c9e7bd069e9-text_block-1","template--16427970003128__c3046b0e-777d-4973-8d1b-4c9e7bd069e9-text_block-2","template--16427970003128__c3046b0e-777d-4973-8d1b-4c9e7bd069e9-text_block-3","5009838a-920c-41bb-841b-9aaa0cae592f"],"disabled":true,"settings":{"title":"","image_height":"natural","desktop_height":450,"mobile_height":300,"align_text":"left","section_padding":"both"}}},"order":["main","3955e9cf-092a-4d98-8aa2-85a1aefe59c8","f3d6a053-ebfa-4f47-8b5c-0fee6dd10511","c5c4b6eb-183a-4948-ad90-980a13999a00","995b3ef3-a555-43d2-b97b-76cdd877f3e9","2300bac2-9528-44fd-affe-daa75994927b","272de21a-56a6-4755-81d8-7a7298faa238","f2596659-4a1e-4118-9e59-3859bf60d9a3","e61f5b2f-1a03-4eb3-b0ae-efdc210e1942","9211a12d-2909-47ea-b914-f722b2f8165c","abbb7a8c-1c28-457b-a3ba-76762653ad0d","d31c151d-d1d9-47de-9f23-17d1f419ab2e","c71ec060-fa78-40ce-8d06-6faee182b131","0154ac85-f24d-46d5-a7ee-3dd67beac47f","22199a26-fc9e-444f-8355-f2169fb48d1f","60fb77ed-b1c5-47d8-9bbb-feff6fd6b6e0","d4d77d60-a718-4e31-8bf9-30b532f88df4","224815b0-1374-4fc2-9830-529d87860f8e","b94bdb77-fcf4-4445-8a21-03b2272b4cec","16b233fb-ee58-4bf7-87d3-b4099738abb6","e143743e-729d-4352-bc7a-898ae7500bfd","669a4369-94cb-4e83-b52f-89949f47c22b","b11e40c1-b710-4c77-8045-19c3c03f7887","241bea62-67a3-4d75-9545-e6a041376c05","c3046b0e-777d-4973-8d1b-4c9e7bd069e9"]}